croudtech_gcp_otel/__init__.py
croudtech_gcp_otel/logging.py
croudtech_gcp_otel/py.typed
croudtech_gcp_otel/telemetry.py
croudtech_python_gcp_otel-1.0.1.dist-info/METADATA
croudtech_python_gcp_otel-1.0.1.dist-info/WHEEL
croudtech_python_gcp_otel-1.0.1.dist-info/RECORD
