Metadata-Version: 2.4
Name: croudtech-python-gcp-otel
Version: 1.0.1
Summary: OpenTelemetry configuration utilities for GCP Cloud Trace and Cloud Logging
Author: CroudTech
Requires-Python: >=3.10,<4.0
Classifier: Programming Language :: Python :: 3
Classifier: Programming Language :: Python :: 3.10
Classifier: Programming Language :: Python :: 3.11
Classifier: Programming Language :: Python :: 3.12
Classifier: Programming Language :: Python :: 3.13
Classifier: Programming Language :: Python :: 3.14
Requires-Dist: opentelemetry-api (>=1.21,<2.0)
Requires-Dist: opentelemetry-exporter-gcp-trace (>=1.6,<2.0)
Requires-Dist: opentelemetry-instrumentation (>=0.42b0)
Requires-Dist: opentelemetry-instrumentation-django (>=0.42b0)
Requires-Dist: opentelemetry-instrumentation-logging (>=0.42b0)
Requires-Dist: opentelemetry-instrumentation-psycopg2 (>=0.42b0)
Requires-Dist: opentelemetry-instrumentation-requests (>=0.42b0)
Requires-Dist: opentelemetry-propagator-gcp (>=1.6,<2.0)
Requires-Dist: opentelemetry-resourcedetector-gcp (>=1.6.0a0,<2.0)
Requires-Dist: opentelemetry-sdk (>=1.21,<2.0)
